bedroc/__init__.py
bedroc/hierarchical.py
bedroc-0.1.0.dist-info/METADATA
bedroc-0.1.0.dist-info/WHEEL
bedroc-0.1.0.dist-info/licenses/LICENSE
bedroc-0.1.0.dist-info/RECORD
