Metadata-Version: 2.4
Name: bedroc
Version: 0.1.0
Summary: Bayesian engine for determining rock origins and compositions
Project-URL: homepage, https://planetology.ethz.ch
Project-URL: documentation, https://bedroc.readthedocs.io/en/latest
Project-URL: repository, https://github.com/ExPlanetology/bedroc
Project-URL: issues, https://github.com/ExPlanetology/bedroc/issues
Author-email: Dan J Bower <dbower@eaps.ethz.ch>
License-Expression: GPL-3.0-or-later
License-File: LICENSE
Requires-Python: <4.0,>=3.11
Requires-Dist: arviz>=0.22.0
Requires-Dist: ipykernel>=7.1.0
Requires-Dist: ipywidgets>=8.1.8
Requires-Dist: pymc>=5.26.1
Requires-Dist: scikit-learn>=1.7.2
Requires-Dist: seaborn>=0.13.2
Provides-Extra: docs
Requires-Dist: doc8>=2.0.0; extra == 'docs'
Requires-Dist: nbsphinx-link>=1.3.1; extra == 'docs'
Requires-Dist: nbsphinx>=0.9.6; extra == 'docs'
Requires-Dist: pypandoc>=1.15; extra == 'docs'
Requires-Dist: setuptools>=80.9.0; extra == 'docs'
Requires-Dist: sphinx-rtd-theme>=3.0.2; extra == 'docs'
Requires-Dist: sphinx>=8.2.3; extra == 'docs'
Requires-Dist: sphinxcontrib-bibtex>=2.6.5; extra == 'docs'
